CommonModules/DataStructure.py
CommonModules/DataStructureOperations.py
CommonModules/IO.py
CommonModules/Log.py
CommonModules/Science.py
CommonModules/Utilities.py
CommonModules/__init__.py
CommonModules-0.1.26.dist-info/LICENSE.txt
CommonModules-0.1.26.dist-info/METADATA
CommonModules-0.1.26.dist-info/WHEEL
CommonModules-0.1.26.dist-info/top_level.txt
CommonModules-0.1.26.dist-info/RECORD
